pdfdrive_api/__init__.py
pdfdrive_api/__main__.py
pdfdrive_api/cli/__init__.py
pdfdrive_api/cli/__main__.py
pdfdrive_api/cli/app.py
pdfdrive_api/cli/commands/__init__.py
pdfdrive_api/cli/commands/download.py
pdfdrive_api/cli/commands/explore.py
pdfdrive_api/cli/commands/search.py
pdfdrive_api/cli/commands/utils.py
pdfdrive_api/constants.py
pdfdrive_api/core/__init__.py
pdfdrive_api/core/book/__init__.py
pdfdrive_api/core/book/constants.py
pdfdrive_api/core/book/extractor.py
pdfdrive_api/core/book/models.py
pdfdrive_api/core/finder/__init__.py
pdfdrive_api/core/finder/extractor.py
pdfdrive_api/core/finder/models.py
pdfdrive_api/download.py
pdfdrive_api/exceptions.py
pdfdrive_api/extras.py
pdfdrive_api/models.py
pdfdrive_api/pages.py
pdfdrive_api/requests.py
pdfdrive_api/types.py
pdfdrive_api/utils.py
pdfdrive_api-0.1.2.dist-info/WHEEL
pdfdrive_api-0.1.2.dist-info/entry_points.txt
pdfdrive_api-0.1.2.dist-info/METADATA
pdfdrive_api-0.1.2.dist-info/RECORD
