Metadata-Version: 2.3
Name: pdfdrive-api
Version: 0.1.2
Summary: Explore, search, and download ebooks programmatically or via CLI
Author: smartwa
Author-email: smartwa <smartwacaleb@gmail.com>
Classifier: License :: OSI Approved :: The Unlicense (Unlicense)
Classifier: Intended Audience :: Developers
Classifier: Operating System :: OS Independent
Classifier: Programming Language :: Python :: 3
Classifier: Programming Language :: Python :: 3.10
Classifier: Programming Language :: Python :: 3.11
Classifier: Programming Language :: Python :: 3.12
Classifier: Programming Language :: Python :: 3.13
Classifier: Programming Language :: Python :: 3.14
Classifier: Topic :: Communications :: File Sharing
Requires-Dist: bs4>=0.0.2
Requires-Dist: httpx>=0.28.1
Requires-Dist: pydantic>=2.12.3
Requires-Dist: throttlebuster>=0.1.11
Requires-Dist: cyclopts>=4.2.1 ; extra == 'cli'
Requires-Python: >=3.10
Provides-Extra: cli
